[{"id":1,"firstName":"Leandra","lastName":"Greiswood","phoneNumber":"214-315-5212","email":"lgreiswood0@vk.com","country":"United States","status":"offline","createAt":"29-Aug-2022"},
{"id":2,"firstName":"Guilbert","lastName":"Gardner","phoneNumber":"254-651-8548","email":"ggardner1@si.edu","country":"United States","status":"offline","createAt":"20-Feb-2022"},
{"id":3,"firstName":"Darlleen","lastName":"Pheasey","phoneNumber":"503-772-0918","email":"dpheasey2@fda.gov","country":"Australia","status":"away","createAt":"15-Mar-2022"},
{"id":4,"firstName":"Darcy","lastName":"Farthing","phoneNumber":"901-134-4218","email":"dfarthing3@sciencedaily.com","country":"United States","status":"online","createAt":"05-Mar-2022"},
{"id":5,"firstName":"Stephine","lastName":"Duchan","phoneNumber":"351-581-1949","email":"sduchan4@washingtonpost.com","country":"Bangladesh","status":"online","createAt":"12-May-2022"},
{"id":6,"firstName":"Ermina","lastName":"Georgiades","phoneNumber":"602-369-4994","email":"egeorgiades5@un.org","country":"United States","status":"away","createAt":"26-Feb-2022"},
{"id":7,"firstName":"Tabbitha","lastName":"Yeld","phoneNumber":"305-505-5840","email":"tyeld6@nyu.edu","country":"United States","status":"offline","createAt":"07-Oct-2022"},
{"id":8,"firstName":"Edik","lastName":"Braganca","phoneNumber":"704-116-4777","email":"ebraganca7@google.co.jp","country":"United States","status":"away","createAt":"14-May-2022"},
{"id":9,"firstName":"Herbie","lastName":"Wreiford","phoneNumber":"260-899-2911","email":"hwreiford8@engadget.com","country":"United States","status":"online","createAt":"08-Nov-2022"},
{"id":10,"firstName":"Josie","lastName":"D'Hooge","phoneNumber":"585-120-4303","email":"jdhooge9@squarespace.com","country":"United States","status":"away","createAt":"10-Oct-2022"},
{"id":11,"firstName":"Nye","lastName":"Jerratsch","phoneNumber":"205-457-2505","email":"njerratscha@infoseek.co.jp","country":"United States","status":"offline","createAt":"18-Feb-2022"},
{"id":12,"firstName":"Charmain","lastName":"Gibbie","phoneNumber":"202-247-7446","email":"cgibbieb@yale.edu","country":"United States","status":"away","createAt":"23-May-2022"},
{"id":13,"firstName":"Kore","lastName":"Auckland","phoneNumber":"316-439-6488","email":"kaucklandc@hostgator.com","country":"Afghanistan","status":"online","createAt":"15-Dec-2021"},
{"id":14,"firstName":"Claudia","lastName":"Teggart","phoneNumber":"281-837-8805","email":"cteggartd@stanford.edu","country":"United States","status":"online","createAt":"18-Sep-2022"},
{"id":15,"firstName":"Tressa","lastName":"Wisbey","phoneNumber":"727-140-3855","email":"twisbeye@census.gov","country":"United States","status":"offline","createAt":"22-Apr-2022"},
{"id":16,"firstName":"Carin","lastName":"Ronald","phoneNumber":"704-748-7636","email":"cronaldf@bigcartel.com","country":"United States","status":"online","createAt":"20-Dec-2021"},
{"id":17,"firstName":"Arlene","lastName":"Cakes","phoneNumber":"214-448-4571","email":"acakesg@ca.gov","country":"United States","status":"online","createAt":"19-Oct-2022"},
{"id":18,"firstName":"Erinna","lastName":"Sworder","phoneNumber":"713-456-5525","email":"esworderh@sbwire.com","country":"United States","status":"offline","createAt":"22-Nov-2022"},
{"id":19,"firstName":"Ulrick","lastName":"Batha","phoneNumber":"312-226-4796","email":"ubathai@alexa.com","country":"United States","status":"away","createAt":"10-Mar-2022"},
{"id":20,"firstName":"Luce","lastName":"Slocom","phoneNumber":"700-779-1876","email":"lslocomj@soup.io","country":"Afghanistan","status":"offline","createAt":"24-Mar-2022"},
{"id":21,"firstName":"Lavinia","lastName":"Dives","phoneNumber":"360-602-3752","email":"ldivesk@cbc.ca","country":"United States","status":"away","createAt":"01-Mar-2022"},
{"id":22,"firstName":"Gus","lastName":"Motion","phoneNumber":"623-322-8596","email":"gmotionl@epa.gov","country":"United States","status":"offline","createAt":"14-Apr-2022"},
{"id":23,"firstName":"Emile","lastName":"Arnald","phoneNumber":"561-326-2434","email":"earnaldm@purevolume.com","country":"United States","status":"away","createAt":"25-Nov-2021"},
{"id":24,"firstName":"Merry","lastName":"Sarah","phoneNumber":"321-242-9786","email":"msarahn@icq.com","country":"United States","status":"online","createAt":"31-Mar-2022"},
{"id":25,"firstName":"Zedekiah","lastName":"Ruddock","phoneNumber":"650-370-5456","email":"zruddocko@cisco.com","country":"United States","status":"offline","createAt":"08-Dec-2021"},
{"id":26,"firstName":"Wenda","lastName":"Beedell","phoneNumber":"702-590-7165","email":"wbeedellp@ehow.com","country":"United States","status":"online","createAt":"02-May-2022"},
{"id":27,"firstName":"Noam","lastName":"Kubat","phoneNumber":"682-588-0369","email":"nkubatq@miibeian.gov.cn","country":"United States","status":"away","createAt":"08-Dec-2021"},
{"id":28,"firstName":"Vincent","lastName":"Balam","phoneNumber":"754-872-9834","email":"vbalamr@ucsd.edu","country":"United States","status":"offline","createAt":"12-Dec-2021"},
{"id":29,"firstName":"Maren","lastName":"Bollins","phoneNumber":"916-919-9007","email":"mbollinss@artisteer.com","country":"United States","status":"offline","createAt":"27-Mar-2022"},
{"id":30,"firstName":"Aylmar","lastName":"Jorczyk","phoneNumber":"739-602-4708","email":"ajorczykt@digg.com","country":"Afghanistan","status":"online","createAt":"31-Jan-2022"},
{"id":31,"firstName":"Gail","lastName":"Robertis","phoneNumber":"504-496-8976","email":"grobertisu@yellowbook.com","country":"United States","status":"online","createAt":"22-Sep-2022"},
{"id":32,"firstName":"Yancy","lastName":"Corzon","phoneNumber":"971-288-5185","email":"ycorzonv@e-recht24.de","country":"United States","status":"away","createAt":"02-Jun-2022"},
{"id":33,"firstName":"Matias","lastName":"Jowers","phoneNumber":"479-499-0974","email":"mjowersw@dell.com","country":"United States","status":"offline","createAt":"04-Feb-2022"},
{"id":34,"firstName":"Evered","lastName":"Jiranek","phoneNumber":"913-535-8108","email":"ejiranekx@arstechnica.com","country":"United States","status":"offline","createAt":"05-Nov-2022"},
{"id":35,"firstName":"Yasmin","lastName":"Hegel","phoneNumber":"815-576-0595","email":"yhegely@xrea.com","country":"United States","status":"online","createAt":"13-Mar-2022"},
{"id":36,"firstName":"Andres","lastName":"Mundell","phoneNumber":"602-516-7203","email":"amundellz@theglobeandmail.com","country":"United States","status":"online","createAt":"03-Oct-2022"},
{"id":37,"firstName":"Oby","lastName":"Braitling","phoneNumber":"916-874-9936","email":"obraitling10@mashable.com","country":"United States","status":"away","createAt":"26-Dec-2021"},
{"id":38,"firstName":"Gare","lastName":"Casini","phoneNumber":"585-110-8023","email":"gcasini11@blogspot.com","country":"United States","status":"offline","createAt":"02-Jun-2022"},
{"id":39,"firstName":"De","lastName":"Ozelton","phoneNumber":"943-705-7978","email":"dozelton12@merriam-webster.com","country":"Afghanistan","status":"away","createAt":"13-Dec-2021"},
{"id":40,"firstName":"Analiese","lastName":"Povele","phoneNumber":"315-901-4166","email":"apovele13@google.de","country":"Afghanistan","status":"online","createAt":"29-Jan-2022"},
{"id":41,"firstName":"Fernanda","lastName":"Maingot","phoneNumber":"770-909-5677","email":"fmaingot14@google.ru","country":"United States","status":"online","createAt":"18-Feb-2022"},
{"id":42,"firstName":"Donica","lastName":"Philipard","phoneNumber":"682-292-6340","email":"dphilipard15@cpanel.net","country":"United States","status":"away","createAt":"01-Nov-2022"},
{"id":43,"firstName":"Colene","lastName":"Micklewicz","phoneNumber":"330-293-9682","email":"cmicklewicz16@hp.com","country":"United States","status":"online","createAt":"30-Oct-2022"},
{"id":44,"firstName":"Marybeth","lastName":"Lamacraft","phoneNumber":"302-836-6084","email":"mlamacraft17@chronoengine.com","country":"United States","status":"offline","createAt":"10-Jan-2022"},
{"id":45,"firstName":"Lissie","lastName":"Downey","phoneNumber":"651-543-9870","email":"ldowney18@squidoo.com","country":"United States","status":"offline","createAt":"18-Apr-2022"},
{"id":46,"firstName":"Siffre","lastName":"Caplen","phoneNumber":"989-120-0434","email":"scaplen19@about.me","country":"Afghanistan","status":"away","createAt":"23-Jul-2022"},
{"id":47,"firstName":"Vittorio","lastName":"Joncic","phoneNumber":"773-327-5826","email":"vjoncic1a@va.gov","country":"United States","status":"away","createAt":"04-Jun-2022"},
{"id":48,"firstName":"Chico","lastName":"Elsay","phoneNumber":"173-630-4544","email":"celsay1b@netlog.com","country":"Afghanistan","status":"away","createAt":"04-Aug-2022"},
{"id":49,"firstName":"Elaina","lastName":"Primak","phoneNumber":"858-835-4345","email":"eprimak1c@shareasale.com","country":"United States","status":"away","createAt":"19-Jun-2022"},
{"id":50,"firstName":"Dalli","lastName":"Garfield","phoneNumber":"206-539-5501","email":"dgarfield1d@infoseek.co.jp","country":"United States","status":"online","createAt":"08-Sep-2022"},
{"id":51,"firstName":"Brewster","lastName":"Pratty","phoneNumber":"520-768-8848","email":"bpratty1e@latimes.com","country":"United States","status":"offline","createAt":"25-Apr-2022"},
{"id":52,"firstName":"Aridatha","lastName":"Stagg","phoneNumber":"714-435-9369","email":"astagg1f@nps.gov","country":"United States","status":"online","createAt":"07-Jan-2022"},
{"id":53,"firstName":"Fowler","lastName":"Deschlein","phoneNumber":"714-717-1435","email":"fdeschlein1g@virginia.edu","country":"United States","status":"offline","createAt":"02-Oct-2022"},
{"id":54,"firstName":"Hubert","lastName":"Dewicke","phoneNumber":"913-837-7434","email":"hdewicke1h@nih.gov","country":"United States","status":"offline","createAt":"01-Sep-2022"},
{"id":55,"firstName":"Kain","lastName":"Charpling","phoneNumber":"317-504-3330","email":"kcharpling1i@microsoft.com","country":"United States","status":"away","createAt":"21-Nov-2022"},
{"id":56,"firstName":"Creight","lastName":"Hinkens","phoneNumber":"612-443-1933","email":"chinkens1j@mysql.com","country":"United States","status":"offline","createAt":"04-Apr-2022"},
{"id":57,"firstName":"Corina","lastName":"Culbard","phoneNumber":"516-421-4453","email":"cculbard1k@theatlantic.com","country":"United States","status":"offline","createAt":"17-Oct-2022"},
{"id":58,"firstName":"Salomo","lastName":"Messer","phoneNumber":"317-808-0255","email":"smesser1l@imdb.com","country":"United States","status":"online","createAt":"15-Feb-2022"},
{"id":59,"firstName":"Engracia","lastName":"Longo","phoneNumber":"480-767-9581","email":"elongo1m@seesaa.net","country":"United States","status":"offline","createAt":"06-Mar-2022"},
{"id":60,"firstName":"Natasha","lastName":"Fulks","phoneNumber":"124-784-6667","email":"nfulks1n@unicef.org","country":"Afghanistan","status":"away","createAt":"10-Mar-2022"},
{"id":61,"firstName":"Rutter","lastName":"Gatty","phoneNumber":"615-452-5030","email":"rgatty1o@diigo.com","country":"Bangladesh","status":"online","createAt":"24-Dec-2021"},
{"id":62,"firstName":"Lindon","lastName":"Witchell","phoneNumber":"262-759-4000","email":"lwitchell1p@msu.edu","country":"United States","status":"offline","createAt":"22-Nov-2022"},
{"id":63,"firstName":"Flori","lastName":"Serrurier","phoneNumber":"334-319-8190","email":"fserrurier1q@biblegateway.com","country":"United States","status":"away","createAt":"03-Aug-2022"},
{"id":64,"firstName":"Stefan","lastName":"Boyan","phoneNumber":"215-192-3683","email":"sboyan1r@mysql.com","country":"United States","status":"away","createAt":"09-Oct-2022"},
{"id":65,"firstName":"Florrie","lastName":"Orts","phoneNumber":"214-721-0950","email":"forts1s@pagesperso-orange.fr","country":"United States","status":"online","createAt":"05-Aug-2022"},
{"id":66,"firstName":"Regan","lastName":"Aylmer","phoneNumber":"908-242-2296","email":"raylmer1t@google.com.hk","country":"Afghanistan","status":"online","createAt":"31-Dec-2021"},
{"id":67,"firstName":"Delaney","lastName":"Witson","phoneNumber":"602-823-2496","email":"dwitson1u@geocities.com","country":"United States","status":"offline","createAt":"26-Apr-2022"},
{"id":68,"firstName":"Dorisa","lastName":"Stefi","phoneNumber":"243-922-8830","email":"dstefi1v@nbcnews.com","country":"Afghanistan","status":"online","createAt":"12-Sep-2022"},
{"id":69,"firstName":"Rhianna","lastName":"Tingey","phoneNumber":"253-187-0904","email":"rtingey1w@webeden.co.uk","country":"United States","status":"away","createAt":"28-Feb-2022"},
{"id":70,"firstName":"Drona","lastName":"Towey","phoneNumber":"967-608-0593","email":"dtowey1x@skyrock.com","country":"Australia","status":"online","createAt":"23-Sep-2022"},
{"id":71,"firstName":"Cleo","lastName":"Hulle","phoneNumber":"520-664-3177","email":"chulle1y@artisteer.com","country":"United States","status":"online","createAt":"13-Mar-2022"},
{"id":72,"firstName":"Trudey","lastName":"Spata","phoneNumber":"601-533-3692","email":"tspata1z@privacy.gov.au","country":"United States","status":"offline","createAt":"03-Dec-2021"},
{"id":73,"firstName":"Adan","lastName":"O'Crotty","phoneNumber":"719-517-9985","email":"aocrotty20@marriott.com","country":"United States","status":"online","createAt":"16-Sep-2022"},
{"id":74,"firstName":"Andria","lastName":"Hassan","phoneNumber":"253-403-9020","email":"ahassan21@spiegel.de","country":"United States","status":"offline","createAt":"04-Jul-2022"},
{"id":75,"firstName":"Olivie","lastName":"Arenson","phoneNumber":"646-607-3232","email":"oarenson22@howstuffworks.com","country":"United States","status":"away","createAt":"11-Jun-2022"},
{"id":76,"firstName":"Gay","lastName":"Acosta","phoneNumber":"557-559-1320","email":"gacosta23@com.com","country":"Bangladesh","status":"away","createAt":"05-May-2022"},
{"id":77,"firstName":"Krysta","lastName":"Wince","phoneNumber":"682-789-2131","email":"kwince24@naver.com","country":"United States","status":"away","createAt":"09-May-2022"},
{"id":78,"firstName":"Wilburt","lastName":"Doerren","phoneNumber":"829-132-9850","email":"wdoerren25@foxnews.com","country":"Afghanistan","status":"away","createAt":"15-Nov-2022"},
{"id":79,"firstName":"Phyllida","lastName":"Ortsmann","phoneNumber":"267-998-8670","email":"portsmann26@symantec.com","country":"United States","status":"online","createAt":"17-Sep-2022"},
{"id":80,"firstName":"Jerrome","lastName":"Tybalt","phoneNumber":"658-644-2977","email":"jtybalt27@ifeng.com","country":"Bangladesh","status":"online","createAt":"17-Dec-2021"},
{"id":81,"firstName":"Estele","lastName":"Hazlewood","phoneNumber":"318-897-6204","email":"ehazlewood28@state.gov","country":"United States","status":"offline","createAt":"17-Jan-2022"},
{"id":82,"firstName":"Jarrod","lastName":"Deek","phoneNumber":"814-122-7038","email":"jdeek29@oaic.gov.au","country":"United States","status":"away","createAt":"05-May-2022"},
{"id":83,"firstName":"Matias","lastName":"Noddles","phoneNumber":"256-770-3284","email":"mnoddles2a@jimdo.com","country":"United States","status":"away","createAt":"09-May-2022"},
{"id":84,"firstName":"Tadd","lastName":"Bagshaw","phoneNumber":"412-808-3298","email":"tbagshaw2b@psu.edu","country":"United States","status":"offline","createAt":"07-Mar-2022"},
{"id":85,"firstName":"Berrie","lastName":"Tottman","phoneNumber":"740-713-4195","email":"btottman2c@globo.com","country":"United States","status":"away","createAt":"16-Dec-2021"},
{"id":86,"firstName":"Findlay","lastName":"Brunsden","phoneNumber":"407-515-7884","email":"fbrunsden2d@apple.com","country":"United States","status":"online","createAt":"23-Sep-2022"},
{"id":87,"firstName":"Agnes","lastName":"Smeath","phoneNumber":"714-729-0508","email":"asmeath2e@slate.com","country":"United States","status":"offline","createAt":"08-Feb-2022"},
{"id":88,"firstName":"Ginnie","lastName":"Glynne","phoneNumber":"916-482-9306","email":"gglynne2f@skyrock.com","country":"United States","status":"offline","createAt":"02-Mar-2022"},
{"id":89,"firstName":"Garik","lastName":"Zmitrichenko","phoneNumber":"561-674-2274","email":"gzmitrichenko2g@taobao.com","country":"United States","status":"offline","createAt":"16-Sep-2022"},
{"id":90,"firstName":"Engelbert","lastName":"Goves","phoneNumber":"443-738-6658","email":"egoves2h@reference.com","country":"United States","status":"offline","createAt":"16-May-2022"},
{"id":91,"firstName":"William","lastName":"Kondratyuk","phoneNumber":"515-983-5503","email":"wkondratyuk2i@imdb.com","country":"United States","status":"offline","createAt":"25-Oct-2022"},
{"id":92,"firstName":"Danny","lastName":"O'Dempsey","phoneNumber":"916-560-9300","email":"dodempsey2j@themeforest.net","country":"United States","status":"online","createAt":"18-Dec-2021"},
{"id":93,"firstName":"Calla","lastName":"Snasel","phoneNumber":"986-714-8194","email":"csnasel2k@hibu.com","country":"Bangladesh","status":"online","createAt":"25-Dec-2021"},
{"id":94,"firstName":"Stafani","lastName":"Heliot","phoneNumber":"812-480-8830","email":"sheliot2l@over-blog.com","country":"United States","status":"away","createAt":"17-May-2022"},
{"id":95,"firstName":"Maridel","lastName":"Vasin","phoneNumber":"313-483-2558","email":"mvasin2m@apache.org","country":"United States","status":"online","createAt":"26-Feb-2022"},
{"id":96,"firstName":"Demetrius","lastName":"Heaps","phoneNumber":"907-131-5208","email":"dheaps2n@bigcartel.com","country":"United States","status":"offline","createAt":"23-Apr-2022"},
{"id":97,"firstName":"Jeffie","lastName":"Grimes","phoneNumber":"253-363-2936","email":"jgrimes2o@businesswire.com","country":"United States","status":"online","createAt":"12-Oct-2022"},
{"id":98,"firstName":"Karrah","lastName":"Vedyasov","phoneNumber":"941-522-0284","email":"kvedyasov2p@dropbox.com","country":"United States","status":"offline","createAt":"10-May-2022"},
{"id":99,"firstName":"Meredith","lastName":"Gornar","phoneNumber":"319-902-3776","email":"mgornar2q@behance.net","country":"United States","status":"offline","createAt":"09-Dec-2021"},
{"id":100,"firstName":"Gerladina","lastName":"Bracknall","phoneNumber":"917-687-2637","email":"gbracknall2r@seattletimes.com","country":"United States","status":"away","createAt":"03-Jun-2022"}]